cubicweb_slickgrid/VERSION
cubicweb_slickgrid/__init__.py
cubicweb_slickgrid/__pkginfo__.py
cubicweb_slickgrid/data/README
cubicweb_slickgrid/data/cubes.slickgrid.css
cubicweb_slickgrid/data/cubes.slickgrid.js
cubicweb_slickgrid/data/cubes.slickgrid.widgets.js
cubicweb_slickgrid/data/icon.png
cubicweb_slickgrid/data/SlickGrid/MIT-LICENSE.txt
cubicweb_slickgrid/data/SlickGrid/slick-default-theme.css
cubicweb_slickgrid/data/SlickGrid/slick.core.js
cubicweb_slickgrid/data/SlickGrid/slick.dataview.js
cubicweb_slickgrid/data/SlickGrid/slick.editors.js
cubicweb_slickgrid/data/SlickGrid/slick.formatters.js
cubicweb_slickgrid/data/SlickGrid/slick.grid.css
cubicweb_slickgrid/data/SlickGrid/slick.grid.js
cubicweb_slickgrid/data/SlickGrid/slick.groupitemmetadataprovider.js
cubicweb_slickgrid/data/SlickGrid/slick.remotemodel.js
cubicweb_slickgrid/data/SlickGrid/controls/slick.columnpicker.css
cubicweb_slickgrid/data/SlickGrid/controls/slick.columnpicker.js
cubicweb_slickgrid/data/SlickGrid/controls/slick.pager.css
cubicweb_slickgrid/data/SlickGrid/controls/slick.pager.js
cubicweb_slickgrid/data/SlickGrid/css/smoothness/jquery-ui-1.8.16.custom.css
cubicweb_slickgrid/data/SlickGrid/css/smoothness/images/ui-bg_flat_0_aaaaaa_40x100.png
cubicweb_slickgrid/data/SlickGrid/css/smoothness/images/ui-bg_flat_75_ffffff_40x100.png
cubicweb_slickgrid/data/SlickGrid/css/smoothness/images/ui-bg_glass_55_fbf9ee_1x400.png
cubicweb_slickgrid/data/SlickGrid/css/smoothness/images/ui-bg_glass_65_ffffff_1x400.png
cubicweb_slickgrid/data/SlickGrid/css/smoothness/images/ui-bg_glass_75_dadada_1x400.png
cubicweb_slickgrid/data/SlickGrid/css/smoothness/images/ui-bg_glass_75_e6e6e6_1x400.png
cubicweb_slickgrid/data/SlickGrid/css/smoothness/images/ui-bg_glass_95_fef1ec_1x400.png
cubicweb_slickgrid/data/SlickGrid/css/smoothness/images/ui-bg_highlight-soft_75_cccccc_1x100.png
cubicweb_slickgrid/data/SlickGrid/css/smoothness/images/ui-icons_222222_256x240.png
cubicweb_slickgrid-1.3.0.dist-info/METADATA
cubicweb_slickgrid-1.3.0.dist-info/WHEEL
cubicweb_slickgrid-1.3.0.dist-info/entry_points.txt
cubicweb_slickgrid-1.3.0.dist-info/top_level.txt
cubicweb_slickgrid-1.3.0.dist-info/RECORD
