Metadata-Version: 2.1
Name: cubicweb-slickgrid
Version: 1.3.0
Summary: Table view rendered using the SlickGrid_ JavaScript library.
Home-page: https://forge.extranet.logilab.fr/cubicweb/cubes/cubicweb-slickgrid
Author: LOGILAB S.A. (Paris, FRANCE)
Author-email: contact@logilab.fr
License: LGPL
Platform: UNKNOWN
Classifier: Environment :: Web Environment
Classifier: Framework :: CubicWeb
Classifier: Programming Language :: Python
Classifier: Programming Language :: Python :: 3
Classifier: Programming Language :: Python :: 3 :: Only
Classifier: Programming Language :: JavaScript
Requires-Python: >=3.7
Requires-Dist: cubicweb (<3.38.0,>=3.26.19)
